eigs.libs/libgomp-a34b3233.so.1.0.0
eigs.libs/liblapack-1ad85175.so.3.4.2
eigs.libs/libgfortran-040039e1.so.5.0.0
eigs.libs/libgfortran-91cc3cb1.so.3.0.0
eigs.libs/libquadmath-96973f99.so.0.0.0
eigs.libs/libblas-357956a1.so.3.4.2
eigs-0.0.3.dist-info/RECORD
eigs-0.0.3.dist-info/METADATA
eigs-0.0.3.dist-info/WHEEL
eigs/eigs.cpython-310-x86_64-linux-gnu.so
eigs/__init__.py
